httpx_kubernetes/__init__.py
httpx_kubernetes-0.1.2.dist-info/METADATA
httpx_kubernetes-0.1.2.dist-info/WHEEL
httpx_kubernetes-0.1.2.dist-info/RECORD
