Metadata-Version: 2.1
Name: httpx-kubernetes
Version: 0.1.2
Summary: Httpx transport that port-forwards into Kubernetes cluster
License: Apache-2.0
Author: Vladislav Wohlrath
Author-email: vladislav@wohlrath.cz
Requires-Python: >=3.9
Classifier: License :: OSI Approved :: Apache Software License
Classifier: Programming Language :: Python :: 3
Classifier: Programming Language :: Python :: 3.9
Classifier: Programming Language :: Python :: 3.10
Classifier: Programming Language :: Python :: 3.11
Classifier: Programming Language :: Python :: 3.12
Classifier: Programming Language :: Python :: 3.13
Requires-Dist: httpx (>=0.20)
Requires-Dist: kubernetes (>=20)
